pyfi_finance/__init__.py
pyfi_finance/cli.py
pyfi_finance/core.py
pyfi_finance/options.py
pyfi_finance/portfolio.py
pyfi_finance/stock.py
pyfi_finance-0.1.1.dist-info/licenses/LICENSE
tests/__init__.py
tests/test_core.py
pyfi_finance-0.1.1.dist-info/METADATA
pyfi_finance-0.1.1.dist-info/WHEEL
pyfi_finance-0.1.1.dist-info/entry_points.txt
pyfi_finance-0.1.1.dist-info/top_level.txt
pyfi_finance-0.1.1.dist-info/RECORD
